{
  "config": {
    "configFile": "e:\\AutomationPlaywright\\playwright.config.ts",
    "rootDir": "e:/AutomationPlaywright",
    "forbidOnly": false,
    "fullyParallel": false,
    "globalSetup": null,
    "globalTeardown": null,
    "globalTimeout": 0,
    "grep": {},
    "grepInvert": null,
    "maxFailures": 0,
    "metadata": {
      "actualWorkers": 1
    },
    "preserveOutput": "always",
    "reporter": [
      [
        "dot",
        null
      ],
      [
        "json",
        {
          "outputFile": "jsonReports/jsonReport.json"
        }
      ],
      [
        "html",
        {
          "open": "never"
        }
      ]
    ],
    "reportSlowTests": {
      "max": 5,
      "threshold": 15000
    },
    "quiet": false,
    "projects": [
      {
        "outputDir": "e:/AutomationPlaywright/test-results",
        "repeatEach": 1,
        "retries": 0,
        "id": "",
        "name": "",
        "testDir": "e:/AutomationPlaywright",
        "testIgnore": [],
        "testMatch": [
          "pomtest/addToCart.test.ts"
        ],
        "timeout": 30000
      }
    ],
    "shard": null,
    "updateSnapshots": "missing",
    "version": "1.40.1",
    "workers": 4,
    "webServer": null
  },
  "suites": [
    {
      "title": "pomtest\\addToCart.test.ts",
      "file": "pomtest/addToCart.test.ts",
      "column": 0,
      "line": 0,
      "specs": [
        {
          "title": "Add to cart test_02",
          "ok": true,
          "tags": [],
          "tests": [
            {
              "timeout": 30000,
              "annotations": [],
              "expectedStatus": "passed",
              "projectId": "",
              "projectName": "",
              "results": [
                {
                  "workerIndex": 0,
                  "status": "passed",
                  "duration": 6361,
                  "errors": [],
                  "stdout": [
                    {
                      "text": "**********************My Account\n"
                    }
                  ],
                  "stderr": [],
                  "retry": 0,
                  "startTime": "2024-01-10T12:22:18.994Z",
                  "attachments": [
                    {
                      "name": "screenshot",
                      "contentType": "image/png",
                      "path": "e:\\AutomationPlaywright\\test-results\\pomtest-addToCart-Add-to-cart-test-02\\test-finished-1.png"
                    },
                    {
                      "name": "video",
                      "contentType": "video/webm",
                      "path": "e:\\AutomationPlaywright\\test-results\\pomtest-addToCart-Add-to-cart-test-02\\video.webm"
                    }
                  ]
                }
              ],
              "status": "expected"
            }
          ],
          "id": "1c188a18f2ecab048a02-e103b082d8494033a50f",
          "file": "pomtest/addToCart.test.ts",
          "line": 35,
          "column": 6
        }
      ]
    }
  ],
  "errors": [],
  "stats": {
    "startTime": "2024-01-10T12:22:17.780Z",
    "duration": 8681.039,
    "expected": 1,
    "skipped": 0,
    "unexpected": 0,
    "flaky": 0
  }
}